[
  {
    "title": "40:17",
    "id": "Hrg0MnyE2jM",
    "link": "https://www.youtube.com/watch?v=Hrg0MnyE2jM",
    "essence": "Sem transcricao disponivel."
  },
  {
    "title": "49:12",
    "id": "cTVXKfYOYxo",
    "link": "https://www.youtube.com/watch?v=cTVXKfYOYxo",
    "essence": "Sem transcricao disponivel."
  },
  {
    "title": "1:30:08",
    "id": "O68y0yRZL1Y",
    "link": "https://www.youtube.com/watch?v=O68y0yRZL1Y",
    "essence": "Sem transcricao disponivel."
  },
  {
    "title": "1:08:18",
    "id": "IDnabc3DjYY",
    "link": "https://www.youtube.com/watch?v=IDnabc3DjYY",
    "essence": "Sem transcricao disponivel."
  },
  {
    "title": "25:17",
    "id": "OkboNGQ9LU0",
    "link": "https://www.youtube.com/watch?v=OkboNGQ9LU0",
    "essence": "Sem transcricao disponivel."
  },
  {
    "title": "21:27",
    "id": "O76ZfAIEukE",
    "link": "https://www.youtube.com/watch?v=O76ZfAIEukE",
    "essence": "Sem transcricao disponivel."
  },
  {
    "title": "43:55",
    "id": "HEaIsKm-pao",
    "link": "https://www.youtube.com/watch?v=HEaIsKm-pao",
    "essence": "Sem transcricao disponivel."
  },
  {
    "title": "47:16",
    "id": "Qjk-cSW-jk4",
    "link": "https://www.youtube.com/watch?v=Qjk-cSW-jk4",
    "essence": "Sem transcricao disponivel."
  },
  {
    "title": "48:28",
    "id": "VKmPGmFY7H4",
    "link": "https://www.youtube.com/watch?v=VKmPGmFY7H4",
    "essence": "Sem transcricao disponivel."
  },
  {
    "title": "1:13:44",
    "id": "sjrW74Hx5Po",
    "link": "https://www.youtube.com/watch?v=sjrW74Hx5Po",
    "essence": "Sem transcricao disponivel."
  },
  {
    "title": "1:35:44",
    "id": "-yGHG3pnHLg",
    "link": "https://www.youtube.com/watch?v=-yGHG3pnHLg",
    "essence": "Sem transcricao disponivel."
  },
  {
    "title": "14:56",
    "id": "CZSGIeRmYn8",
    "link": "https://www.youtube.com/watch?v=CZSGIeRmYn8",
    "essence": "Sem transcricao disponivel."
  },
  {
    "title": "1:14:10",
    "id": "iAA8NrfQtHo",
    "link": "https://www.youtube.com/watch?v=iAA8NrfQtHo",
    "essence": "Sem transcricao disponivel."
  },
  {
    "title": "1:10:53",
    "id": "yfEhz9poqW8",
    "link": "https://www.youtube.com/watch?v=yfEhz9poqW8",
    "essence": "Sem transcricao disponivel."
  },
  {
    "title": "1:39:10",
    "id": "EifK2a_5K_U",
    "link": "https://www.youtube.com/watch?v=EifK2a_5K_U&pp=0gcJCQMLAYcqIYzv",
    "essence": "Sem transcricao disponivel."
  }
]